freight_forwarder/__init__.py
freight_forwarder/config.py
freight_forwarder/const.py
freight_forwarder/container_ship.py
freight_forwarder/freight_forwarder.py
freight_forwarder/image.py
freight_forwarder/long_shoremen.py
freight_forwarder/cli/__init__.py
freight_forwarder/cli/cli_mixin.py
freight_forwarder/cli/deploy.py
freight_forwarder/cli/export.py
freight_forwarder/cli/info.py
freight_forwarder/cli/marshaling_yard.py
freight_forwarder/cli/offload.py
freight_forwarder/cli/quality_control.py
freight_forwarder/cli/test.py
freight_forwarder/commercial_invoice/__init__.py
freight_forwarder/commercial_invoice/commercial_invoice.py
freight_forwarder/commercial_invoice/container_dict.py
freight_forwarder/commercial_invoice/injector.py
freight_forwarder/commercial_invoice/service.py
freight_forwarder/container/__init__.py
freight_forwarder/container/config.py
freight_forwarder/container/container.py
freight_forwarder/container/host_config.py
freight_forwarder/registry/__init__.py
freight_forwarder/registry/auth.py
freight_forwarder/registry/exceptions.py
freight_forwarder/registry/registry.py
freight_forwarder/registry/registry_base.py
freight_forwarder/utils/__init__.py
freight_forwarder/utils/logger.py
freight_forwarder/utils/utils.py
freight_forwarder-1.0.3.data/scripts/freight-forwarder
freight_forwarder-1.0.3.dist-info/DESCRIPTION.rst
freight_forwarder-1.0.3.dist-info/METADATA
freight_forwarder-1.0.3.dist-info/metadata.json
freight_forwarder-1.0.3.dist-info/RECORD
freight_forwarder-1.0.3.dist-info/top_level.txt
freight_forwarder-1.0.3.dist-info/WHEEL
plugins/__init__.py
