Metadata-Version: 2.0
Name: freight-forwarder
Version: 1.0.3
Summary: Python client and CLI to aid in CI/CD workflow using Docker.
Home-page: https://github.com/TuneOSS/freight_forwarder
Author: Alex Banna
Author-email: alexb@tune.com
License: UNKNOWN
Platform: UNKNOWN
Classifier: Development Status :: 4 - Beta
Classifier: License :: OSI Approved :: MIT License
Classifier: Natural Language :: English
Classifier: Intended Audience :: Developers
Classifier: Intended Audience :: System Administrators
Classifier: Operating System :: OS Independent
Classifier: Programming Language :: Python
Classifier: Programming Language :: Python :: 2.7
Classifier: Programming Language :: Python :: 3.4
Classifier: Topic :: Utilities
Requires-Dist: docker-py (>=1.6.0)
Requires-Dist: ipaddress (==1.0.16)
Requires-Dist: requests (>=2.5.3)
Requires-Dist: python-dateutil (>=2.4.0)
Requires-Dist: six (>=1.9.0)
Requires-Dist: pyyaml (==3.10)
Requires-Dist: argparse (==1.3.0)
Requires-Dist: psutil (==3.4.2)
